atomstructutils/__init__.py
atomstructutils/bibtex.py
atomstructutils/constants.py
atomstructutils/protocols.conf
atomstructutils/wizards.py
atomstructutils/protocols/__init__.py
atomstructutils/protocols/protocol_convertsymmetry.py
atomstructutils/protocols/protocol_operate.py
atomstructutils/tests/__init__.py
atomstructutils/tests/test_protocol_convertsymmetry.py
atomstructutils/tests/test_protocol_operate.py
atomstructutils/viewers/__init__.py
atomstructutils/viewers/viewer.py
scipion_em_atomstructutils-3.0.3.dist-info/LICENSE
scipion_em_atomstructutils-3.0.3.dist-info/METADATA
scipion_em_atomstructutils-3.0.3.dist-info/WHEEL
scipion_em_atomstructutils-3.0.3.dist-info/entry_points.txt
scipion_em_atomstructutils-3.0.3.dist-info/top_level.txt
scipion_em_atomstructutils-3.0.3.dist-info/RECORD
