Metadata-Version: 2.1
Name: scipion-em-atomstructutils
Version: 3.0.3
Summary: A Scipion plugin to manipulate atomic structure files (PDB/MMCIF)
Home-page: https://github.com/scipion-em/scipion-em-atomstructutils
Author: Roberto Marabini and Marta Martinez
Author-email: scipion@cnb.csic.es
License: UNKNOWN
Keywords: scipion pdb  scipion-3
Platform: UNKNOWN
Requires-Dist: scipion-em-chimera (>=3.0.0)
